rdbbeat/__init__.py
rdbbeat/controller.py
rdbbeat/data_models.py
rdbbeat/exceptions.py
rdbbeat/py.typed
rdbbeat/schedulers.py
rdbbeat/settings.py
rdbbeat/tzcrontab.py
rdbbeat/db/__init__.py
rdbbeat/db/models.py
rdbbeat/db/migrations/__init__.py
rdbbeat/db/migrations/env.py
rdbbeat/db/migrations/versions/2022_03_16_added_crontab_periodic_task_tables.py
rdbbeat/db/migrations/versions/__init__.py
rdbbeat-0.2.1.dist-info/LICENSE
rdbbeat-0.2.1.dist-info/METADATA
rdbbeat-0.2.1.dist-info/WHEEL
rdbbeat-0.2.1.dist-info/top_level.txt
rdbbeat-0.2.1.dist-info/RECORD
