Metadata-Version: 2.1
Name: rdbbeat
Version: 0.2.1
Summary: A SQLAlchemy-based scheduler for celery-beat
Home-page: https://github.com/aruba-uxi/celery-sqlalchemy-scheduler
Author: Aruba UXI
License: MIT
Classifier: Intended Audience :: Developers
Classifier: Operating System :: OS Independent
Classifier: Programming Language :: Python :: 3.10
Classifier: Programming Language :: Python :: 3.9
Classifier: Programming Language :: Python :: 3.8
Classifier: Programming Language :: Python :: 3
Requires-Python: >=3.8
License-File: LICENSE
Requires-Dist: celery~=5.2
Requires-Dist: sqlalchemy
Requires-Dist: alembic
Requires-Dist: pydantic
Requires-Dist: python-dotenv
Requires-Dist: pytz
